{
  "name": "create_ltab:pillage/streets",
  "elements": [
    {
      "element": {
        "element_type": "minecraft:legacy_single_pool_element",
        "location": "create_ltab:pillage/streets/corner_01",
        "processors": "minecraft:street_plains",
        "projection": "terrain_matching"
      },
      "weight": 2
    },
    {
      "element": {
        "element_type": "minecraft:legacy_single_pool_element",
        "location": "create_ltab:pillage/streets/corner_02",
        "processors": "minecraft:street_plains",
        "projection": "terrain_matching"
      },
      "weight": 2
    },
    {
      "element": {
        "element_type": "minecraft:legacy_single_pool_element",
        "location": "create_ltab:pillage/streets/crossroad_01",
        "processors": "minecraft:street_plains",
        "projection": "terrain_matching"
      },
      "weight": 2
    },
    {
      "element": {
        "element_type": "minecraft:legacy_single_pool_element",
        "location": "create_ltab:pillage/streets/straight_01",
        "processors": "minecraft:street_plains",
        "projection": "terrain_matching"
      },
      "weight": 4
    },
    {
      "element": {
        "element_type": "minecraft:legacy_single_pool_element",
        "location": "create_ltab:pillage/streets/straight_02",
        "processors": "minecraft:street_plains",
        "projection": "terrain_matching"
      },
      "weight": 4
    },
    {
      "element": {
        "element_type": "minecraft:legacy_single_pool_element",
        "location": "create_ltab:pillage/streets/straight_03",
        "processors": "minecraft:street_plains",
        "projection": "terrain_matching"
      },
      "weight": 7
    },
    {
      "element": {
        "element_type": "minecraft:legacy_single_pool_element",
        "location": "create_ltab:pillage/streets/straight_04",
        "processors": "minecraft:street_plains",
        "projection": "terrain_matching"
      },
      "weight": 7
    }
  ],
  "fallback": "minecraft:empty"
}